chorder/__init__.py
chorder/formatter.py
chorder/main.py
galshaya_chorder-0.1.0.dist-info/LICENSE
galshaya_chorder-0.1.0.dist-info/METADATA
galshaya_chorder-0.1.0.dist-info/WHEEL
galshaya_chorder-0.1.0.dist-info/entry_points.txt
galshaya_chorder-0.1.0.dist-info/top_level.txt
galshaya_chorder-0.1.0.dist-info/RECORD
